cli
clia
constants
regex
