Metadata-Version: 2.1
Name: clia
Version: 0.1.1
Summary: CLIA - Command Line Intelligent Assistant
Home-page: https://github.com/singhgautam7/CLIA---Command-Line-Intelligent-Assistant
Author: Gautam Rajeev Singh
Author-email: gautamsingh1997@gmail.com
License: MIT
Keywords: pyton cli assistant
Platform: UNKNOWN
Classifier: Programming Language :: Python :: 3
Classifier: License :: OSI Approved :: MIT License
Classifier: Operating System :: OS Independent
Requires-Python: >=3.6
License-File: LICENSE.txt
